pie_modules/__init__.py
pie_modules/annotations.py
pie_modules/document/__init__.py
pie_modules/document/processing/__init__.py
pie_modules/document/processing/merge_multi_spans.py
pie_modules/document/processing/merge_spans_via_relation.py
pie_modules/document/processing/regex_partitioner.py
pie_modules/document/processing/relation_argument_sorter.py
pie_modules/document/processing/sentence_splitter.py
pie_modules/document/processing/text_pair.py
pie_modules/document/processing/text_span_trimmer.py
pie_modules/document/processing/tokenization.py
pie_modules/documents.py
pie_modules/metrics/__init__.py
pie_modules/metrics/confusion_matrix.py
pie_modules/metrics/f1.py
pie_modules/metrics/relation_argument_distance_collector.py
pie_modules/metrics/span_coverage_collector.py
pie_modules/metrics/span_length_collector.py
pie_modules/metrics/squad_f1.py
pie_modules/metrics/statistics.py
pie_modules/models/__init__.py
pie_modules/models/base_models/__init__.py
pie_modules/models/base_models/bart_as_pointer_network.py
pie_modules/models/base_models/bart_with_decoder_position_ids.py
pie_modules/models/common/__init__.py
pie_modules/models/common/has_taskmodule.py
pie_modules/models/common/model_with_boilerplate.py
pie_modules/models/common/model_with_metrics_from_taskmodule.py
pie_modules/models/common/stages.py
pie_modules/models/components/__init__.py
pie_modules/models/components/pointer_head.py
pie_modules/models/components/pooler.py
pie_modules/models/components/seq2seq_encoder.py
pie_modules/models/interface.py
pie_modules/models/sequence_classification_with_pooler.py
pie_modules/models/simple_extractive_question_answering.py
pie_modules/models/simple_generative.py
pie_modules/models/simple_sequence_classification.py
pie_modules/models/simple_token_classification.py
pie_modules/models/span_tuple_classification.py
pie_modules/models/token_classification_with_seq2seq_encoder_and_crf.py
pie_modules/taskmodules/__init__.py
pie_modules/taskmodules/common/__init__.py
pie_modules-0.15.13.dist-info/LICENSE
pie_modules-0.15.13.dist-info/METADATA
pie_modules-0.15.13.dist-info/WHEEL
pie_modules-0.15.13.dist-info/RECORD
