Metadata-Version: 2.1
Name: pie-modules
Version: 0.15.13
Summary: Model and Taskmodule implementations for PyTorch-IE
Home-page: https://github.com/arnebinder/pie-modules
Author: Arne Binder
Author-email: arne.binder@dfki.de
Requires-Python: >=3.9,<4.0
Classifier: Framework :: Pytest
Classifier: Programming Language :: Python
Classifier: Programming Language :: Python :: 3
Classifier: Programming Language :: Python :: 3.9
Classifier: Programming Language :: Python :: 3.10
Classifier: Programming Language :: Python :: 3.11
Classifier: Programming Language :: Python :: 3 :: Only
Requires-Dist: pytorch-ie (>=0.31.9,<0.33.0)
Requires-Dist: pytorch-lightning (>=2.1.0,<3.0.0)
Requires-Dist: torchmetrics (>=1,<2)
Requires-Dist: transformers (>=4.35.0,<4.37.0)
Project-URL: Bug Tracker, https://github.com/arnebinder/pie-modules/issues
Project-URL: Changelog, https://github.com/arnebinder/pie-modules/releases
Project-URL: Repository, https://github.com/arnebinder/pie-modules
